pyenergenie3/__init__.py
pyenergenie3/core.py
tests/__init__.py
tests/test_pyenergenie3.py
pyenergenie3-0.1.0.dist-info/METADATA
pyenergenie3-0.1.0.dist-info/WHEEL
pyenergenie3-0.1.0.dist-info/top_level.txt
pyenergenie3-0.1.0.dist-info/RECORD
